pythreejs/__init__.py
pythreejs/_example_helper.py
pythreejs/_package.py
pythreejs/_version.py
pythreejs/enums.py
pythreejs/install.py
pythreejs/pythreejs.py
pythreejs/sage.py
pythreejs/traits.py
pythreejs/_base/Three.py
pythreejs/_base/__init__.py
pythreejs/_base/renderable.py
pythreejs/_base/uniforms.py
pythreejs/animation/AnimationAction.py
pythreejs/animation/AnimationAction_autogen.py
pythreejs/animation/AnimationClip_autogen.py
pythreejs/animation/AnimationMixer_autogen.py
pythreejs/animation/AnimationObjectGroup_autogen.py
pythreejs/animation/AnimationUtils_autogen.py
pythreejs/animation/KeyframeTrack_autogen.py
pythreejs/animation/PropertyBinding_autogen.py
pythreejs/animation/PropertyMixer_autogen.py
pythreejs/animation/__init__.py
pythreejs/animation/tracks/BooleanKeyframeTrack_autogen.py
pythreejs/animation/tracks/ColorKeyframeTrack_autogen.py
pythreejs/animation/tracks/NumberKeyframeTrack_autogen.py
pythreejs/animation/tracks/QuaternionKeyframeTrack_autogen.py
pythreejs/animation/tracks/StringKeyframeTrack_autogen.py
pythreejs/animation/tracks/VectorKeyframeTrack_autogen.py
pythreejs/animation/tracks/__init__.py
pythreejs/audio/AudioAnalyser_autogen.py
pythreejs/audio/AudioListener_autogen.py
pythreejs/audio/Audio_autogen.py
pythreejs/audio/PositionalAudio_autogen.py
pythreejs/audio/__init__.py
pythreejs/cameras/ArrayCamera_autogen.py
pythreejs/cameras/Camera_autogen.py
pythreejs/cameras/CombinedCamera_autogen.py
pythreejs/cameras/CubeCamera_autogen.py
pythreejs/cameras/OrthographicCamera_autogen.py
pythreejs/cameras/PerspectiveCamera_autogen.py
pythreejs/cameras/StereoCamera_autogen.py
pythreejs/cameras/__init__.py
pythreejs/controls/Controls_autogen.py
pythreejs/controls/FlyControls_autogen.py
pythreejs/controls/OrbitControls.py
pythreejs/controls/OrbitControls_autogen.py
pythreejs/controls/Picker_autogen.py
pythreejs/controls/TrackballControls_autogen.py
pythreejs/controls/__init__.py
pythreejs/core/BaseBufferGeometry_autogen.py
pythreejs-2.4.1.dist-info/LICENSE
pythreejs-2.4.1.dist-info/METADATA
pythreejs-2.4.1.dist-info/WHEEL
pythreejs-2.4.1.dist-info/top_level.txt
pythreejs-2.4.1.dist-info/RECORD
