Metadata-Version: 2.1
Name: pythreejs
Version: 2.4.1
Summary: Interactive 3D graphics for the Jupyter Notebook and JupyterLab, using Three.js and Jupyter Widgets.
Home-page: https://github.com/jupyter-widgets/pythreejs
Author: PyThreejs Development Team
Author-email: jason@jasongrout.org
License: BSD-3-Clause
Keywords: ipython,jupyter,widgets,webgl,graphics,3d
Classifier: Development Status :: 5 - Production/Stable
Classifier: Intended Audience :: Developers
Classifier: Intended Audience :: Science/Research
Classifier: Topic :: Multimedia :: Graphics
Classifier: License :: OSI Approved :: BSD License
Classifier: Programming Language :: Python :: 2
Classifier: Programming Language :: Python :: 3
Classifier: Programming Language :: JavaScript
Requires-Python: >=3.7
License-File: LICENSE
Requires-Dist: ipywidgets (>=7.2.1)
Requires-Dist: ipydatawidgets (>=1.1.1)
Requires-Dist: numpy
Requires-Dist: traitlets
Provides-Extra: docs
Requires-Dist: sphinx (>=1.5) ; extra == 'docs'
Requires-Dist: nbsphinx (>=0.2.13) ; extra == 'docs'
Requires-Dist: nbsphinx-link ; extra == 'docs'
Requires-Dist: sphinx-rtd-theme ; extra == 'docs'
Provides-Extra: examples
Requires-Dist: scipy ; extra == 'examples'
Requires-Dist: matplotlib ; extra == 'examples'
Requires-Dist: scikit-image ; extra == 'examples'
Requires-Dist: ipywebrtc ; extra == 'examples'
Provides-Extra: test
Requires-Dist: nbval ; extra == 'test'
Requires-Dist: pytest-check-links ; extra == 'test'
Requires-Dist: numpy (>=1.14) ; extra == 'test'
